proof_wala/__init__.py
proof_wala/data/prompts/conversation/copra-coq-dfs.md
proof_wala/data/prompts/conversation/eqn_solver.md
proof_wala/data/prompts/conversation/simple_math.md
proof_wala/data/prompts/system/copra-coq-dfs.md
proof_wala/data/prompts/system/eqn_solver.md
proof_wala/data/prompts/system/simple_math.md
proof_wala/data/proofs/coq/simple1/Makefile
proof_wala/data/proofs/coq/simple1/_CoqProject
proof_wala/data/proofs/coq/simple1/defns.v
proof_wala/data/proofs/coq/simple1/thms.v
proof_wala/data/proofs/coq/simple2/thms.v
proof_wala/data/proofs/lean/lean4_proj/Lean4Proj.lean
proof_wala/data/proofs/lean/lean4_proj/lake-manifest.json
proof_wala/data/proofs/lean/lean4_proj/lakefile.lean
proof_wala/data/proofs/lean/lean4_proj/lean-toolchain
proof_wala/data/proofs/lean/lean4_proj/Lean4Proj/Basic.lean
proof_wala/itp/__init__.py
proof_wala/itp/codet5_training_data_formatter.py
proof_wala/itp/copra_training_data_formatter.py
proof_wala/itp/proof_model_training_data_formatter.py
proof_wala/itp/training_data_formatter.py
proof_wala/llm_helpers/__init__.py
proof_wala/llm_helpers/comet_helper.py
proof_wala/llm_helpers/convert_llama_weights_to_hf.py
proof_wala/llm_helpers/cuda_context.py
proof_wala/llm_helpers/custom_s2s_trainer.py
proof_wala/llm_helpers/custom_sft_trainer.py
proof_wala/llm_helpers/huggingface_model_map.py
proof_wala/llm_helpers/llama2_chat_format.py
proof_wala/llm_helpers/llama_chatbot.py
proof_wala/llm_helpers/model.py
proof_wala/llm_helpers/tgi_model.py
proof_wala/llm_helpers/tgi_server.py
proof_wala/llm_helpers/theorem_proving_training_dataset.py
proof_wala/main/__init__.py
proof_wala/main/config.py
proof_wala/main/eval_config.py
proof_wala/main/init_ray.py
proof_wala/main/run.py
proof_wala/main/run_inferences.py
proof_wala/main/run_proof_search.py
proof_wala/main/run_token_count.py
proof_wala/main/run_training.py
proof_wala/main/config/INT_experiment.yaml
proof_wala/main/config/__init__.py
proof_wala/main/config/compcert_chat_experiment.yaml
proof_wala-1.1.9.dist-info/METADATA
proof_wala-1.1.9.dist-info/WHEEL
proof_wala-1.1.9.dist-info/entry_points.txt
proof_wala-1.1.9.dist-info/RECORD
