Metadata-Version: 2.4
Name: proof-wala
Version: 1.1.9
Summary: Python library for training LLMs with Interactive Theorem Proving data.
Project-URL: Homepage, https://github.com/trishullab/proof-wala
Project-URL: Issues, https://github.com/trishullab/proof-wala/issues
Author-email: Amitayush Thakur <amitayush@utexas.edu>
Classifier: License :: OSI Approved :: MIT License
Classifier: Operating System :: POSIX :: Linux
Classifier: Programming Language :: Python :: 3
Requires-Python: <3.13,>=3.9
Requires-Dist: accelerate==1.3.0
Requires-Dist: bitsandbytes==0.41.1
Requires-Dist: comet-ml==3.33.9
Requires-Dist: filelock==3.12.4
Requires-Dist: gradio>=5.11.0
Requires-Dist: graphviz==0.17
Requires-Dist: itp-interface==1.1.9
Requires-Dist: parglare==0.16.1
Requires-Dist: peft==0.7.1
Requires-Dist: protobuf>=3.20.3
Requires-Dist: pydantic>=2.10.6
Requires-Dist: scipy==1.11.2
Requires-Dist: sentencepiece==0.1.99
Requires-Dist: spaces==0.16.1
Requires-Dist: transformers==4.48.0
Requires-Dist: trl==0.14.0
